{
	"cdmVersionRange" : ">=5.0.0",
	"PrimaryCriteria" : {
		"CriteriaList" : [
			{
				"ProcedureOccurrence" : {
					"CorrelatedCriteria" : {
						"Type" : "ALL",
						"CriteriaList" : [
							{
								"Criteria" : {
									"ConditionOccurrence" : {
										"CodesetId" : 33,
										"ConditionTypeExclude" : false
									}
								},
								"StartWindow" : {
									"Start" : {
										"Days" : 365,
										"Coeff" : -1
									},
									"End" : {
										"Days" : 30,
										"Coeff" : 1
									},
									"UseIndexEnd" : false,
									"UseEventEnd" : false
								},
								"RestrictVisit" : false,
								"IgnoreObservationPeriod" : false,
								"Occurrence" : {
									"Type" : 2,
									"Count" : 1,
									"IsDistinct" : false
								}
							}
						],
						"DemographicCriteriaList" : [],
						"Groups" : []
					},
					"CodesetId" : 34,
					"ProcedureTypeExclude" : false,
					"Age" : {
						"Value" : 55,
						"Op" : "gte"
					},
					"Gender" : [
						{
							"CONCEPT_ID" : 8532,
							"CONCEPT_NAME" : "FEMALE",
							"STANDARD_CONCEPT" : null,
							"STANDARD_CONCEPT_CAPTION" : "Unknown",
							"INVALID_REASON" : null,
							"INVALID_REASON_CAPTION" : "Unknown",
							"CONCEPT_CODE" : "F",
							"DOMAIN_ID" : "Gender",
							"VOCABULARY_ID" : "Gender",
							"CONCEPT_CLASS_ID" : null
						}
					]
				}
			},
			{
				"ProcedureOccurrence" : {
					"CorrelatedCriteria" : {
						"Type" : "ALL",
						"CriteriaList" : [
							{
								"Criteria" : {
									"ConditionOccurrence" : {
										"CodesetId" : 33,
										"ConditionTypeExclude" : false
									}
								},
								"StartWindow" : {
									"Start" : {
										"Days" : 365,
										"Coeff" : -1
									},
									"End" : {
										"Days" : 30,
										"Coeff" : 1
									},
									"UseIndexEnd" : false,
									"UseEventEnd" : false
								},
								"RestrictVisit" : false,
								"IgnoreObservationPeriod" : false,
								"Occurrence" : {
									"Type" : 2,
									"Count" : 1,
									"IsDistinct" : false
								}
							}
						],
						"DemographicCriteriaList" : [],
						"Groups" : []
					},
					"ProcedureTypeExclude" : false,
					"ProcedureSourceConcept" : 34,
					"Age" : {
						"Value" : 55,
						"Op" : "gte"
					},
					"Gender" : [
						{
							"CONCEPT_ID" : 8532,
							"CONCEPT_NAME" : "FEMALE",
							"STANDARD_CONCEPT" : null,
							"STANDARD_CONCEPT_CAPTION" : "Unknown",
							"INVALID_REASON" : null,
							"INVALID_REASON_CAPTION" : "Unknown",
							"CONCEPT_CODE" : "F",
							"DOMAIN_ID" : "Gender",
							"VOCABULARY_ID" : "Gender",
							"CONCEPT_CLASS_ID" : null
						}
					]
				}
			}
		],
		"ObservationWindow" : {
			"PriorDays" : 0,
			"PostDays" : 0
		},
		"PrimaryCriteriaLimit" : {
			"Type" : "First"
		}
	},
	"ConceptSets" : [
		{
			"id" : 33,
			"name" : "[MSK_AI]outcome_oa_thumb",
			"expression" : {
				"items" : [
					{
						"concept" : {
							"CONCEPT_ID" : 36713091,
							"CONCEPT_NAME" : "Bilateral osteoarthritis of first carpometacarpal joint",
							"STANDARD_CONCEPT" : "S",
							"STANDARD_CONCEPT_CAPTION" : "Standard",
							"INVALID_REASON" : "V",
							"INVALID_REASON_CAPTION" : "Valid",
							"CONCEPT_CODE" : "303041000119104",
							"DOMAIN_ID" : "Condition",
							"VOCABULARY_ID" : "SNOMED",
							"CONCEPT_CLASS_ID" : "Clinical Finding"
						},
						"isExcluded" : false,
						"includeDescendants" : true,
						"includeMapped" : false
					},
					{
						"concept" : {
							"CONCEPT_ID" : 762329,
							"CONCEPT_NAME" : "Osteoarthritis of first carpometacarpal joint of left hand",
							"STANDARD_CONCEPT" : "S",
							"STANDARD_CONCEPT_CAPTION" : "Standard",
							"INVALID_REASON" : "V",
							"INVALID_REASON_CAPTION" : "Valid",
							"CONCEPT_CODE" : "323251000119103",
							"DOMAIN_ID" : "Condition",
							"VOCABULARY_ID" : "SNOMED",
							"CONCEPT_CLASS_ID" : "Clinical Finding"
						},
						"isExcluded" : false,
						"includeDescendants" : true,
						"includeMapped" : false
					},
					{
						"concept" : {
							"CONCEPT_ID" : 762330,
							"CONCEPT_NAME" : "Osteoarthritis of first carpometacarpal joint of right hand",
							"STANDARD_CONCEPT" : "S",
							"STANDARD_CONCEPT_CAPTION" : "Standard",
							"INVALID_REASON" : "V",
							"INVALID_REASON_CAPTION" : "Valid",
							"CONCEPT_CODE" : "323261000119101",
							"DOMAIN_ID" : "Condition",
							"VOCABULARY_ID" : "SNOMED",
							"CONCEPT_CLASS_ID" : "Clinical Finding"
						},
						"isExcluded" : false,
						"includeDescendants" : true,
						"includeMapped" : false
					},
					{
						"concept" : {
							"CONCEPT_ID" : 4242103,
							"CONCEPT_NAME" : "Osteoarthrosis of the carpometacarpal joint of the thumb",
							"STANDARD_CONCEPT" : "S",
							"STANDARD_CONCEPT_CAPTION" : "Standard",
							"INVALID_REASON" : "V",
							"INVALID_REASON_CAPTION" : "Valid",
							"CONCEPT_CODE" : "37895003",
							"DOMAIN_ID" : "Condition",
							"VOCABULARY_ID" : "SNOMED",
							"CONCEPT_CLASS_ID" : "Clinical Finding"
						},
						"isExcluded" : false,
						"includeDescendants" : true,
						"includeMapped" : false
					}
				]
			}
		},
		{
			"id" : 34,
			"name" : "[MSK-AI] thumb oa surgery (arthrodesis,arthroscopy, arthroplasty, injection)_updated",
			"expression" : {
				"items" : [
					{
						"concept" : {
							"CONCEPT_ID" : 4169228,
							"CONCEPT_NAME" : "Arthrodesis of carpometacarpal joint of thumb",
							"STANDARD_CONCEPT" : "S",
							"STANDARD_CONCEPT_CAPTION" : "Standard",
							"INVALID_REASON" : "V",
							"INVALID_REASON_CAPTION" : "Valid",
							"CONCEPT_CODE" : "48909003",
							"DOMAIN_ID" : "Procedure",
							"VOCABULARY_ID" : "SNOMED",
							"CONCEPT_CLASS_ID" : "Procedure"
						},
						"isExcluded" : false,
						"includeDescendants" : true,
						"includeMapped" : false
					},
					{
						"concept" : {
							"CONCEPT_ID" : 2005926,
							"CONCEPT_NAME" : "Arthroplasty and repair of hand, fingers, and wrist",
							"STANDARD_CONCEPT" : "S",
							"STANDARD_CONCEPT_CAPTION" : "Standard",
							"INVALID_REASON" : "V",
							"INVALID_REASON_CAPTION" : "Valid",
							"CONCEPT_CODE" : "81.7",
							"DOMAIN_ID" : "Procedure",
							"VOCABULARY_ID" : "ICD9Proc",
							"CONCEPT_CLASS_ID" : "3-dig nonbill code"
						},
						"isExcluded" : false,
						"includeDescendants" : true,
						"includeMapped" : false
					},
					{
						"concept" : {
							"CONCEPT_ID" : 2005930,
							"CONCEPT_NAME" : "Arthroplasty of carpocarpal or carpometacarpal joint with implant",
							"STANDARD_CONCEPT" : "S",
							"STANDARD_CONCEPT_CAPTION" : "Standard",
							"INVALID_REASON" : "V",
							"INVALID_REASON_CAPTION" : "Valid",
							"CONCEPT_CODE" : "81.74",
							"DOMAIN_ID" : "Procedure",
							"VOCABULARY_ID" : "ICD9Proc",
							"CONCEPT_CLASS_ID" : "4-dig billing code"
						},
						"isExcluded" : false,
						"includeDescendants" : true,
						"includeMapped" : false
					},
					{
						"concept" : {
							"CONCEPT_ID" : 2005931,
							"CONCEPT_NAME" : "Arthroplasty of carpocarpal or carpometacarpal joint without implant",
							"STANDARD_CONCEPT" : "S",
							"STANDARD_CONCEPT_CAPTION" : "Standard",
							"INVALID_REASON" : "V",
							"INVALID_REASON_CAPTION" : "Valid",
							"CONCEPT_CODE" : "81.75",
							"DOMAIN_ID" : "Procedure",
							"VOCABULARY_ID" : "ICD9Proc",
							"CONCEPT_CLASS_ID" : "4-dig billing code"
						},
						"isExcluded" : false,
						"includeDescendants" : true,
						"includeMapped" : false
					},
					{
						"concept" : {
							"CONCEPT_ID" : 4034398,
							"CONCEPT_NAME" : "Arthroplasty of the carpometacarpal joint of the thumb",
							"STANDARD_CONCEPT" : "S",
							"STANDARD_CONCEPT_CAPTION" : "Standard",
							"INVALID_REASON" : "V",
							"INVALID_REASON_CAPTION" : "Valid",
							"CONCEPT_CODE" : "239477000",
							"DOMAIN_ID" : "Procedure",
							"VOCABULARY_ID" : "SNOMED",
							"CONCEPT_CLASS_ID" : "Procedure"
						},
						"isExcluded" : false,
						"includeDescendants" : true,
						"includeMapped" : false
					},
					{
						"concept" : {
							"CONCEPT_ID" : 2005659,
							"CONCEPT_NAME" : "Arthroscopy, hand and finger",
							"STANDARD_CONCEPT" : "N",
							"STANDARD_CONCEPT_CAPTION" : "Non-Standard",
							"INVALID_REASON" : "V",
							"INVALID_REASON_CAPTION" : "Valid",
							"CONCEPT_CODE" : "80.24",
							"DOMAIN_ID" : "Procedure",
							"VOCABULARY_ID" : "ICD9Proc",
							"CONCEPT_CLASS_ID" : "4-dig billing code"
						},
						"isExcluded" : false,
						"includeDescendants" : true,
						"includeMapped" : false
					},
					{
						"concept" : {
							"CONCEPT_ID" : 4182095,
							"CONCEPT_NAME" : "Injection of steroid into carpometacarpal joint of thumb",
							"STANDARD_CONCEPT" : "S",
							"STANDARD_CONCEPT_CAPTION" : "Standard",
							"INVALID_REASON" : "V",
							"INVALID_REASON_CAPTION" : "Valid",
							"CONCEPT_CODE" : "429518005",
							"DOMAIN_ID" : "Procedure",
							"VOCABULARY_ID" : "SNOMED",
							"CONCEPT_CLASS_ID" : "Procedure"
						},
						"isExcluded" : false,
						"includeDescendants" : true,
						"includeMapped" : false
					},
					{
						"concept" : {
							"CONCEPT_ID" : 2005962,
							"CONCEPT_NAME" : "Injection of therapeutic substance into joint or ligament",
							"STANDARD_CONCEPT" : "S",
							"STANDARD_CONCEPT_CAPTION" : "Standard",
							"INVALID_REASON" : "V",
							"INVALID_REASON_CAPTION" : "Valid",
							"CONCEPT_CODE" : "81.92",
							"DOMAIN_ID" : "Procedure",
							"VOCABULARY_ID" : "ICD9Proc",
							"CONCEPT_CLASS_ID" : "4-dig billing code"
						},
						"isExcluded" : false,
						"includeDescendants" : true,
						"includeMapped" : false
					}
				]
			}
		}
	],
	"QualifiedLimit" : {
		"Type" : "First"
	},
	"ExpressionLimit" : {
		"Type" : "First"
	},
	"InclusionRules" : [],
	"CensoringCriteria" : [],
	"CollapseSettings" : {
		"CollapseType" : "ERA",
		"EraPad" : 0
	},
	"CensorWindow" : {}
}