{
	"cdmVersionRange" : ">=5.0.0",
	"PrimaryCriteria" : {
		"CriteriaList" : [
			{
				"ProcedureOccurrence" : {
					"CorrelatedCriteria" : {
						"Type" : "ALL",
						"CriteriaList" : [
							{
								"Criteria" : {
									"ConditionOccurrence" : {
										"CodesetId" : 34,
										"ConditionTypeExclude" : false
									}
								},
								"StartWindow" : {
									"Start" : {
										"Days" : 365,
										"Coeff" : -1
									},
									"End" : {
										"Days" : 30,
										"Coeff" : 1
									},
									"UseIndexEnd" : false,
									"UseEventEnd" : false
								},
								"RestrictVisit" : false,
								"IgnoreObservationPeriod" : false,
								"Occurrence" : {
									"Type" : 2,
									"Count" : 1,
									"IsDistinct" : false
								}
							}
						],
						"DemographicCriteriaList" : [],
						"Groups" : []
					},
					"CodesetId" : 33,
					"ProcedureTypeExclude" : false
				}
			}
		],
		"ObservationWindow" : {
			"PriorDays" : 0,
			"PostDays" : 0
		},
		"PrimaryCriteriaLimit" : {
			"Type" : "First"
		}
	},
	"AdditionalCriteria" : {
		"Type" : "ALL",
		"CriteriaList" : [],
		"DemographicCriteriaList" : [
			{}
		],
		"Groups" : []
	},
	"ConceptSets" : [
		{
			"id" : 33,
			"name" : "[MSK_AI]outcome_oa_procedure_all_updated - OPTIMIZED",
			"expression" : {
				"items" : [
					{
						"concept" : {
							"CONCEPT_ID" : 4102136,
							"CONCEPT_NAME" : "Acromioplasty for recurrent dislocation of shoulder",
							"STANDARD_CONCEPT" : "S",
							"STANDARD_CONCEPT_CAPTION" : "Standard",
							"INVALID_REASON" : "V",
							"INVALID_REASON_CAPTION" : "Valid",
							"CONCEPT_CODE" : "28052009",
							"DOMAIN_ID" : "Procedure",
							"VOCABULARY_ID" : "SNOMED",
							"CONCEPT_CLASS_ID" : "Procedure"
						},
						"isExcluded" : true,
						"includeDescendants" : false,
						"includeMapped" : false
					},
					{
						"concept" : {
							"CONCEPT_ID" : 4114318,
							"CONCEPT_NAME" : "Arthrodesis of finger",
							"STANDARD_CONCEPT" : "S",
							"STANDARD_CONCEPT_CAPTION" : "Standard",
							"INVALID_REASON" : "V",
							"INVALID_REASON_CAPTION" : "Valid",
							"CONCEPT_CODE" : "300023000",
							"DOMAIN_ID" : "Procedure",
							"VOCABULARY_ID" : "SNOMED",
							"CONCEPT_CLASS_ID" : "Procedure"
						},
						"isExcluded" : false,
						"includeDescendants" : true,
						"includeMapped" : false
					},
					{
						"concept" : {
							"CONCEPT_ID" : 4114320,
							"CONCEPT_NAME" : "Arthrodesis of thumb",
							"STANDARD_CONCEPT" : "S",
							"STANDARD_CONCEPT_CAPTION" : "Standard",
							"INVALID_REASON" : "V",
							"INVALID_REASON_CAPTION" : "Valid",
							"CONCEPT_CODE" : "300031005",
							"DOMAIN_ID" : "Procedure",
							"VOCABULARY_ID" : "SNOMED",
							"CONCEPT_CLASS_ID" : "Procedure"
						},
						"isExcluded" : false,
						"includeDescendants" : true,
						"includeMapped" : false
					},
					{
						"concept" : {
							"CONCEPT_ID" : 45888520,
							"CONCEPT_NAME" : "Arthrodesis, carpometacarpal joint, thumb, with or without internal fixation",
							"STANDARD_CONCEPT" : "C",
							"STANDARD_CONCEPT_CAPTION" : "Classification",
							"INVALID_REASON" : "V",
							"INVALID_REASON_CAPTION" : "Valid",
							"CONCEPT_CODE" : "1014103",
							"DOMAIN_ID" : "Procedure",
							"VOCABULARY_ID" : "CPT4",
							"CONCEPT_CLASS_ID" : "CPT4 Hierarchy"
						},
						"isExcluded" : false,
						"includeDescendants" : true,
						"includeMapped" : false
					},
					{
						"concept" : {
							"CONCEPT_ID" : 45888185,
							"CONCEPT_NAME" : "Arthrodesis, interphalangeal joint, with or without internal fixation",
							"STANDARD_CONCEPT" : "C",
							"STANDARD_CONCEPT_CAPTION" : "Classification",
							"INVALID_REASON" : "V",
							"INVALID_REASON_CAPTION" : "Valid",
							"CONCEPT_CODE" : "1014106",
							"DOMAIN_ID" : "Procedure",
							"VOCABULARY_ID" : "CPT4",
							"CONCEPT_CLASS_ID" : "CPT4 Hierarchy"
						},
						"isExcluded" : false,
						"includeDescendants" : true,
						"includeMapped" : false
					},
					{
						"concept" : {
							"CONCEPT_ID" : 45889047,
							"CONCEPT_NAME" : "Arthrodesis, metacarpophalangeal joint, with or without internal fixation",
							"STANDARD_CONCEPT" : "C",
							"STANDARD_CONCEPT_CAPTION" : "Classification",
							"INVALID_REASON" : "V",
							"INVALID_REASON_CAPTION" : "Valid",
							"CONCEPT_CODE" : "1014105",
							"DOMAIN_ID" : "Procedure",
							"VOCABULARY_ID" : "CPT4",
							"CONCEPT_CLASS_ID" : "CPT4 Hierarchy"
						},
						"isExcluded" : false,
						"includeDescendants" : true,
						"includeMapped" : false
					},
					{
						"concept" : {
							"CONCEPT_ID" : 4305812,
							"CONCEPT_NAME" : "Arthroplasty of hand",
							"STANDARD_CONCEPT" : "S",
							"STANDARD_CONCEPT_CAPTION" : "Standard",
							"INVALID_REASON" : "V",
							"INVALID_REASON_CAPTION" : "Valid",
							"CONCEPT_CODE" : "83007002",
							"DOMAIN_ID" : "Procedure",
							"VOCABULARY_ID" : "SNOMED",
							"CONCEPT_CLASS_ID" : "Procedure"
						},
						"isExcluded" : false,
						"includeDescendants" : true,
						"includeMapped" : false
					},
					{
						"concept" : {
							"CONCEPT_ID" : 4306618,
							"CONCEPT_NAME" : "Arthroplasty of hip with bone graft",
							"STANDARD_CONCEPT" : "S",
							"STANDARD_CONCEPT_CAPTION" : "Standard",
							"INVALID_REASON" : "V",
							"INVALID_REASON_CAPTION" : "Valid",
							"CONCEPT_CODE" : "83381006",
							"DOMAIN_ID" : "Procedure",
							"VOCABULARY_ID" : "SNOMED",
							"CONCEPT_CLASS_ID" : "Procedure"
						},
						"isExcluded" : false,
						"includeDescendants" : true,
						"includeMapped" : false
					},
					{
						"concept" : {
							"CONCEPT_ID" : 4078547,
							"CONCEPT_NAME" : "Arthroplasty of knee",
							"STANDARD_CONCEPT" : "S",
							"STANDARD_CONCEPT_CAPTION" : "Standard",
							"INVALID_REASON" : "V",
							"INVALID_REASON_CAPTION" : "Valid",
							"CONCEPT_CODE" : "19063003",
							"DOMAIN_ID" : "Procedure",
							"VOCABULARY_ID" : "SNOMED",
							"CONCEPT_CLASS_ID" : "Procedure"
						},
						"isExcluded" : false,
						"includeDescendants" : true,
						"includeMapped" : false
					},
					{
						"concept" : {
							"CONCEPT_ID" : 4034665,
							"CONCEPT_NAME" : "Arthroplasty of shoulder",
							"STANDARD_CONCEPT" : "S",
							"STANDARD_CONCEPT_CAPTION" : "Standard",
							"INVALID_REASON" : "V",
							"INVALID_REASON_CAPTION" : "Valid",
							"CONCEPT_CODE" : "239468007",
							"DOMAIN_ID" : "Procedure",
							"VOCABULARY_ID" : "SNOMED",
							"CONCEPT_CLASS_ID" : "Procedure"
						},
						"isExcluded" : false,
						"includeDescendants" : true,
						"includeMapped" : false
					},
					{
						"concept" : {
							"CONCEPT_ID" : 45888673,
							"CONCEPT_NAME" : "Arthroplasty, femoral condyles or tibial plateau(s), knee",
							"STANDARD_CONCEPT" : "C",
							"STANDARD_CONCEPT_CAPTION" : "Classification",
							"INVALID_REASON" : "V",
							"INVALID_REASON_CAPTION" : "Valid",
							"CONCEPT_CODE" : "1014119",
							"DOMAIN_ID" : "Procedure",
							"VOCABULARY_ID" : "CPT4",
							"CONCEPT_CLASS_ID" : "CPT4 Hierarchy"
						},
						"isExcluded" : false,
						"includeDescendants" : true,
						"includeMapped" : false
					},
					{
						"concept" : {
							"CONCEPT_ID" : 45888310,
							"CONCEPT_NAME" : "Arthroplasty, glenohumeral joint",
							"STANDARD_CONCEPT" : "C",
							"STANDARD_CONCEPT_CAPTION" : "Classification",
							"INVALID_REASON" : "V",
							"INVALID_REASON_CAPTION" : "Valid",
							"CONCEPT_CODE" : "1004224",
							"DOMAIN_ID" : "Procedure",
							"VOCABULARY_ID" : "CPT4",
							"CONCEPT_CLASS_ID" : "CPT4 Hierarchy"
						},
						"isExcluded" : false,
						"includeDescendants" : true,
						"includeMapped" : false
					},
					{
						"concept" : {
							"CONCEPT_ID" : 45890558,
							"CONCEPT_NAME" : "Arthroplasty, knee, condyle and plateau",
							"STANDARD_CONCEPT" : "C",
							"STANDARD_CONCEPT_CAPTION" : "Classification",
							"INVALID_REASON" : "V",
							"INVALID_REASON_CAPTION" : "Valid",
							"CONCEPT_CODE" : "1005073",
							"DOMAIN_ID" : "Procedure",
							"VOCABULARY_ID" : "CPT4",
							"CONCEPT_CLASS_ID" : "CPT4 Hierarchy"
						},
						"isExcluded" : false,
						"includeDescendants" : true,
						"includeMapped" : false
					},
					{
						"concept" : {
							"CONCEPT_ID" : 45888521,
							"CONCEPT_NAME" : "Arthroplasty, knee, tibial plateau",
							"STANDARD_CONCEPT" : "C",
							"STANDARD_CONCEPT_CAPTION" : "Classification",
							"INVALID_REASON" : "V",
							"INVALID_REASON_CAPTION" : "Valid",
							"CONCEPT_CODE" : "1014118",
							"DOMAIN_ID" : "Procedure",
							"VOCABULARY_ID" : "CPT4",
							"CONCEPT_CLASS_ID" : "CPT4 Hierarchy"
						},
						"isExcluded" : false,
						"includeDescendants" : true,
						"includeMapped" : false
					},
					{
						"concept" : {
							"CONCEPT_ID" : 45889826,
							"CONCEPT_NAME" : "Arthroplasty, patella",
							"STANDARD_CONCEPT" : "C",
							"STANDARD_CONCEPT_CAPTION" : "Classification",
							"INVALID_REASON" : "V",
							"INVALID_REASON_CAPTION" : "Valid",
							"CONCEPT_CODE" : "1005065",
							"DOMAIN_ID" : "Procedure",
							"VOCABULARY_ID" : "CPT4",
							"CONCEPT_CLASS_ID" : "CPT4 Hierarchy"
						},
						"isExcluded" : false,
						"includeDescendants" : true,
						"includeMapped" : false
					},
					{
						"concept" : {
							"CONCEPT_ID" : 4288878,
							"CONCEPT_NAME" : "Arthroscopy of hip",
							"STANDARD_CONCEPT" : "S",
							"STANDARD_CONCEPT_CAPTION" : "Standard",
							"INVALID_REASON" : "V",
							"INVALID_REASON_CAPTION" : "Valid",
							"CONCEPT_CODE" : "69650005",
							"DOMAIN_ID" : "Procedure",
							"VOCABULARY_ID" : "SNOMED",
							"CONCEPT_CLASS_ID" : "Procedure"
						},
						"isExcluded" : false,
						"includeDescendants" : true,
						"includeMapped" : false
					},
					{
						"concept" : {
							"CONCEPT_ID" : 4205229,
							"CONCEPT_NAME" : "Arthroscopy of knee",
							"STANDARD_CONCEPT" : "S",
							"STANDARD_CONCEPT_CAPTION" : "Standard",
							"INVALID_REASON" : "V",
							"INVALID_REASON_CAPTION" : "Valid",
							"CONCEPT_CODE" : "309431009",
							"DOMAIN_ID" : "Procedure",
							"VOCABULARY_ID" : "SNOMED",
							"CONCEPT_CLASS_ID" : "Procedure"
						},
						"isExcluded" : false,
						"includeDescendants" : true,
						"includeMapped" : false
					},
					{
						"concept" : {
							"CONCEPT_ID" : 2005659,
							"CONCEPT_NAME" : "Arthroscopy, hand and finger",
							"STANDARD_CONCEPT" : "N",
							"STANDARD_CONCEPT_CAPTION" : "Non-Standard",
							"INVALID_REASON" : "V",
							"INVALID_REASON_CAPTION" : "Valid",
							"CONCEPT_CODE" : "80.24",
							"DOMAIN_ID" : "Procedure",
							"VOCABULARY_ID" : "ICD9Proc",
							"CONCEPT_CLASS_ID" : "4-dig billing code"
						},
						"isExcluded" : false,
						"includeDescendants" : true,
						"includeMapped" : false
					},
					{
						"concept" : {
							"CONCEPT_ID" : 45889893,
							"CONCEPT_NAME" : "Arthroscopy, hip, surgical",
							"STANDARD_CONCEPT" : "C",
							"STANDARD_CONCEPT_CAPTION" : "Classification",
							"INVALID_REASON" : "V",
							"INVALID_REASON_CAPTION" : "Valid",
							"CONCEPT_CODE" : "1005648",
							"DOMAIN_ID" : "Procedure",
							"VOCABULARY_ID" : "CPT4",
							"CONCEPT_CLASS_ID" : "CPT4 Hierarchy"
						},
						"isExcluded" : false,
						"includeDescendants" : true,
						"includeMapped" : false
					},
					{
						"concept" : {
							"CONCEPT_ID" : 45887571,
							"CONCEPT_NAME" : "Arthroscopy, knee, surgical",
							"STANDARD_CONCEPT" : "C",
							"STANDARD_CONCEPT_CAPTION" : "Classification",
							"INVALID_REASON" : "V",
							"INVALID_REASON_CAPTION" : "Valid",
							"CONCEPT_CODE" : "1005657",
							"DOMAIN_ID" : "Procedure",
							"VOCABULARY_ID" : "CPT4",
							"CONCEPT_CLASS_ID" : "CPT4 Hierarchy"
						},
						"isExcluded" : false,
						"includeDescendants" : true,
						"includeMapped" : false
					},
					{
						"concept" : {
							"CONCEPT_ID" : 2721113,
							"CONCEPT_NAME" : "Arthroscopy, knee, surgical for harvesting of cartilage (chondrocyte cells)",
							"STANDARD_CONCEPT" : "S",
							"STANDARD_CONCEPT_CAPTION" : "Standard",
							"INVALID_REASON" : "V",
							"INVALID_REASON_CAPTION" : "Valid",
							"CONCEPT_CODE" : "S2112",
							"DOMAIN_ID" : "Procedure",
							"VOCABULARY_ID" : "HCPCS",
							"CONCEPT_CLASS_ID" : "HCPCS"
						},
						"isExcluded" : false,
						"includeDescendants" : true,
						"includeMapped" : false
					},
					{
						"concept" : {
							"CONCEPT_ID" : 2617368,
							"CONCEPT_NAME" : "Arthroscopy, knee, surgical, for removal of loose body, foreign body, debridement/shaving of articular cartilage (chondroplasty) at the time of other surgical knee arthroscopy in a different compartment of the same knee",
							"STANDARD_CONCEPT" : "S",
							"STANDARD_CONCEPT_CAPTION" : "Standard",
							"INVALID_REASON" : "V",
							"INVALID_REASON_CAPTION" : "Valid",
							"CONCEPT_CODE" : "G0289",
							"DOMAIN_ID" : "Procedure",
							"VOCABULARY_ID" : "HCPCS",
							"CONCEPT_CLASS_ID" : "HCPCS"
						},
						"isExcluded" : false,
						"includeDescendants" : true,
						"includeMapped" : false
					},
					{
						"concept" : {
							"CONCEPT_ID" : 42739911,
							"CONCEPT_NAME" : "Arthroscopy, knee, surgical, implantation of osteochondral graft(s) for treatment of articular surface defect; allografts (Deprecated)",
							"STANDARD_CONCEPT" : "S",
							"STANDARD_CONCEPT_CAPTION" : "Standard",
							"INVALID_REASON" : "V",
							"INVALID_REASON_CAPTION" : "Valid",
							"CONCEPT_CODE" : "0013T",
							"DOMAIN_ID" : "Procedure",
							"VOCABULARY_ID" : "CPT4",
							"CONCEPT_CLASS_ID" : "CPT4"
						},
						"isExcluded" : false,
						"includeDescendants" : true,
						"includeMapped" : false
					},
					{
						"concept" : {
							"CONCEPT_ID" : 42739910,
							"CONCEPT_NAME" : "Arthroscopy, knee, surgical, implantation of osteochondral graft(s) for treatment of articular surface defect; autografts (Deprecated)",
							"STANDARD_CONCEPT" : "S",
							"STANDARD_CONCEPT_CAPTION" : "Standard",
							"INVALID_REASON" : "V",
							"INVALID_REASON_CAPTION" : "Valid",
							"CONCEPT_CODE" : "0012T",
							"DOMAIN_ID" : "Procedure",
							"VOCABULARY_ID" : "CPT4",
							"CONCEPT_CLASS_ID" : "CPT4"
						},
						"isExcluded" : false,
						"includeDescendants" : true,
						"includeMapped" : false
					},
					{
						"concept" : {
							"CONCEPT_ID" : 2106073,
							"CONCEPT_NAME" : "Arthroscopy, metacarpophalangeal joint, surgical; with debridement",
							"STANDARD_CONCEPT" : "S",
							"STANDARD_CONCEPT_CAPTION" : "Standard",
							"INVALID_REASON" : "V",
							"INVALID_REASON_CAPTION" : "Valid",
							"CONCEPT_CODE" : "29901",
							"DOMAIN_ID" : "Procedure",
							"VOCABULARY_ID" : "CPT4",
							"CONCEPT_CLASS_ID" : "CPT4"
						},
						"isExcluded" : false,
						"includeDescendants" : true,
						"includeMapped" : false
					},
					{
						"concept" : {
							"CONCEPT_ID" : 2105048,
							"CONCEPT_NAME" : "Arthrotomy with meniscus repair, knee",
							"STANDARD_CONCEPT" : "S",
							"STANDARD_CONCEPT_CAPTION" : "Standard",
							"INVALID_REASON" : "V",
							"INVALID_REASON_CAPTION" : "Valid",
							"CONCEPT_CODE" : "27403",
							"DOMAIN_ID" : "Procedure",
							"VOCABULARY_ID" : "CPT4",
							"CONCEPT_CLASS_ID" : "CPT4"
						},
						"isExcluded" : true,
						"includeDescendants" : false,
						"includeMapped" : false
					},
					{
						"concept" : {
							"CONCEPT_ID" : 4214724,
							"CONCEPT_NAME" : "Arthrotomy with open meniscus repair",
							"STANDARD_CONCEPT" : "S",
							"STANDARD_CONCEPT_CAPTION" : "Standard",
							"INVALID_REASON" : "V",
							"INVALID_REASON_CAPTION" : "Valid",
							"CONCEPT_CODE" : "80486001",
							"DOMAIN_ID" : "Procedure",
							"VOCABULARY_ID" : "SNOMED",
							"CONCEPT_CLASS_ID" : "Procedure"
						},
						"isExcluded" : true,
						"includeDescendants" : false,
						"includeMapped" : false
					},
					{
						"concept" : {
							"CONCEPT_ID" : 4010250,
							"CONCEPT_NAME" : "Diagnostic arthroscopy of knee with synovial biopsy",
							"STANDARD_CONCEPT" : "S",
							"STANDARD_CONCEPT_CAPTION" : "Standard",
							"INVALID_REASON" : "V",
							"INVALID_REASON_CAPTION" : "Valid",
							"CONCEPT_CODE" : "112767006",
							"DOMAIN_ID" : "Procedure",
							"VOCABULARY_ID" : "SNOMED",
							"CONCEPT_CLASS_ID" : "Procedure"
						},
						"isExcluded" : false,
						"includeDescendants" : true,
						"includeMapped" : false
					},
					{
						"concept" : {
							"CONCEPT_ID" : 40481169,
							"CONCEPT_NAME" : "Extracapsular repair of tear of anterior cruciate ligament using suture stabilization and fiber tape implant",
							"STANDARD_CONCEPT" : "S",
							"STANDARD_CONCEPT_CAPTION" : "Standard",
							"INVALID_REASON" : "V",
							"INVALID_REASON_CAPTION" : "Valid",
							"CONCEPT_CODE" : "444889008",
							"DOMAIN_ID" : "Procedure",
							"VOCABULARY_ID" : "SNOMED",
							"CONCEPT_CLASS_ID" : "Procedure"
						},
						"isExcluded" : true,
						"includeDescendants" : false,
						"includeMapped" : false
					},
					{
						"concept" : {
							"CONCEPT_ID" : 4002377,
							"CONCEPT_NAME" : "Hand injection",
							"STANDARD_CONCEPT" : "S",
							"STANDARD_CONCEPT_CAPTION" : "Standard",
							"INVALID_REASON" : "V",
							"INVALID_REASON_CAPTION" : "Valid",
							"CONCEPT_CODE" : "119650007",
							"DOMAIN_ID" : "Procedure",
							"VOCABULARY_ID" : "SNOMED",
							"CONCEPT_CLASS_ID" : "Procedure"
						},
						"isExcluded" : false,
						"includeDescendants" : true,
						"includeMapped" : false
					},
					{
						"concept" : {
							"CONCEPT_ID" : 4160581,
							"CONCEPT_NAME" : "Hydrodistention of glenohumeral joint using fluoroscopic guidance",
							"STANDARD_CONCEPT" : "S",
							"STANDARD_CONCEPT_CAPTION" : "Standard",
							"INVALID_REASON" : "V",
							"INVALID_REASON_CAPTION" : "Valid",
							"CONCEPT_CODE" : "431322006",
							"DOMAIN_ID" : "Procedure",
							"VOCABULARY_ID" : "SNOMED",
							"CONCEPT_CLASS_ID" : "Procedure"
						},
						"isExcluded" : true,
						"includeDescendants" : false,
						"includeMapped" : false
					},
					{
						"concept" : {
							"CONCEPT_ID" : 4128362,
							"CONCEPT_NAME" : "Injection into shoulder joint",
							"STANDARD_CONCEPT" : "S",
							"STANDARD_CONCEPT_CAPTION" : "Standard",
							"INVALID_REASON" : "V",
							"INVALID_REASON_CAPTION" : "Valid",
							"CONCEPT_CODE" : "290035003",
							"DOMAIN_ID" : "Procedure",
							"VOCABULARY_ID" : "SNOMED",
							"CONCEPT_CLASS_ID" : "Procedure"
						},
						"isExcluded" : false,
						"includeDescendants" : true,
						"includeMapped" : false
					},
					{
						"concept" : {
							"CONCEPT_ID" : 40481441,
							"CONCEPT_NAME" : "Injection of both knee joints",
							"STANDARD_CONCEPT" : "S",
							"STANDARD_CONCEPT_CAPTION" : "Standard",
							"INVALID_REASON" : "V",
							"INVALID_REASON_CAPTION" : "Valid",
							"CONCEPT_CODE" : "443387005",
							"DOMAIN_ID" : "Procedure",
							"VOCABULARY_ID" : "SNOMED",
							"CONCEPT_CLASS_ID" : "Procedure"
						},
						"isExcluded" : false,
						"includeDescendants" : true,
						"includeMapped" : false
					},
					{
						"concept" : {
							"CONCEPT_ID" : 4031174,
							"CONCEPT_NAME" : "Injection of hip joint",
							"STANDARD_CONCEPT" : "S",
							"STANDARD_CONCEPT_CAPTION" : "Standard",
							"INVALID_REASON" : "V",
							"INVALID_REASON_CAPTION" : "Valid",
							"CONCEPT_CODE" : "14381006",
							"DOMAIN_ID" : "Procedure",
							"VOCABULARY_ID" : "SNOMED",
							"CONCEPT_CLASS_ID" : "Procedure"
						},
						"isExcluded" : false,
						"includeDescendants" : true,
						"includeMapped" : false
					},
					{
						"concept" : {
							"CONCEPT_ID" : 4103962,
							"CONCEPT_NAME" : "Injection of knee joint",
							"STANDARD_CONCEPT" : "S",
							"STANDARD_CONCEPT_CAPTION" : "Standard",
							"INVALID_REASON" : "V",
							"INVALID_REASON_CAPTION" : "Valid",
							"CONCEPT_CODE" : "300024006",
							"DOMAIN_ID" : "Procedure",
							"VOCABULARY_ID" : "SNOMED",
							"CONCEPT_CLASS_ID" : "Procedure"
						},
						"isExcluded" : false,
						"includeDescendants" : true,
						"includeMapped" : false
					},
					{
						"concept" : {
							"CONCEPT_ID" : 4034298,
							"CONCEPT_NAME" : "Interposition arthroplasty of the hip",
							"STANDARD_CONCEPT" : "S",
							"STANDARD_CONCEPT_CAPTION" : "Standard",
							"INVALID_REASON" : "V",
							"INVALID_REASON_CAPTION" : "Valid",
							"CONCEPT_CODE" : "239500004",
							"DOMAIN_ID" : "Procedure",
							"VOCABULARY_ID" : "SNOMED",
							"CONCEPT_CLASS_ID" : "Procedure"
						},
						"isExcluded" : false,
						"includeDescendants" : true,
						"includeMapped" : false
					},
					{
						"concept" : {
							"CONCEPT_ID" : 44807403,
							"CONCEPT_NAME" : "Ligament reconstruction of carpometacarpal joint of thumb",
							"STANDARD_CONCEPT" : "S",
							"STANDARD_CONCEPT_CAPTION" : "Standard",
							"INVALID_REASON" : "V",
							"INVALID_REASON_CAPTION" : "Valid",
							"CONCEPT_CODE" : "816881000000102",
							"DOMAIN_ID" : "Procedure",
							"VOCABULARY_ID" : "SNOMED",
							"CONCEPT_CLASS_ID" : "Procedure"
						},
						"isExcluded" : true,
						"includeDescendants" : true,
						"includeMapped" : false
					},
					{
						"concept" : {
							"CONCEPT_ID" : 40481475,
							"CONCEPT_NAME" : "Open reduction of dislocation of knee with external fixation and repair of ligament",
							"STANDARD_CONCEPT" : "S",
							"STANDARD_CONCEPT_CAPTION" : "Standard",
							"INVALID_REASON" : "V",
							"INVALID_REASON_CAPTION" : "Valid",
							"CONCEPT_CODE" : "443417003",
							"DOMAIN_ID" : "Procedure",
							"VOCABULARY_ID" : "SNOMED",
							"CONCEPT_CLASS_ID" : "Procedure"
						},
						"isExcluded" : true,
						"includeDescendants" : false,
						"includeMapped" : false
					},
					{
						"concept" : {
							"CONCEPT_ID" : 40482763,
							"CONCEPT_NAME" : "Open reduction of dislocation of knee with internal fixation and repair of ligament",
							"STANDARD_CONCEPT" : "S",
							"STANDARD_CONCEPT_CAPTION" : "Standard",
							"INVALID_REASON" : "V",
							"INVALID_REASON_CAPTION" : "Valid",
							"CONCEPT_CODE" : "443660002",
							"DOMAIN_ID" : "Procedure",
							"VOCABULARY_ID" : "SNOMED",
							"CONCEPT_CLASS_ID" : "Procedure"
						},
						"isExcluded" : true,
						"includeDescendants" : false,
						"includeMapped" : false
					},
					{
						"concept" : {
							"CONCEPT_ID" : 4148237,
							"CONCEPT_NAME" : "Patellar stabilization by tendon transfer",
							"STANDARD_CONCEPT" : "S",
							"STANDARD_CONCEPT_CAPTION" : "Standard",
							"INVALID_REASON" : "V",
							"INVALID_REASON_CAPTION" : "Valid",
							"CONCEPT_CODE" : "34861006",
							"DOMAIN_ID" : "Procedure",
							"VOCABULARY_ID" : "SNOMED",
							"CONCEPT_CLASS_ID" : "Procedure"
						},
						"isExcluded" : true,
						"includeDescendants" : false,
						"includeMapped" : false
					},
					{
						"concept" : {
							"CONCEPT_ID" : 40488933,
							"CONCEPT_NAME" : "Plication of medial patellar retinaculum",
							"STANDARD_CONCEPT" : "S",
							"STANDARD_CONCEPT_CAPTION" : "Standard",
							"INVALID_REASON" : "V",
							"INVALID_REASON_CAPTION" : "Valid",
							"CONCEPT_CODE" : "448246005",
							"DOMAIN_ID" : "Procedure",
							"VOCABULARY_ID" : "SNOMED",
							"CONCEPT_CLASS_ID" : "Procedure"
						},
						"isExcluded" : true,
						"includeDescendants" : false,
						"includeMapped" : false
					},
					{
						"concept" : {
							"CONCEPT_ID" : 4322299,
							"CONCEPT_NAME" : "Primary repair of collateral ligament of metacarpophalangeal joint",
							"STANDARD_CONCEPT" : "S",
							"STANDARD_CONCEPT_CAPTION" : "Standard",
							"INVALID_REASON" : "V",
							"INVALID_REASON_CAPTION" : "Valid",
							"CONCEPT_CODE" : "70234001",
							"DOMAIN_ID" : "Procedure",
							"VOCABULARY_ID" : "SNOMED",
							"CONCEPT_CLASS_ID" : "Procedure"
						},
						"isExcluded" : true,
						"includeDescendants" : false,
						"includeMapped" : false
					},
					{
						"concept" : {
							"CONCEPT_ID" : 4218075,
							"CONCEPT_NAME" : "Primary repair of collateral ligament of metacarpophalangeal joint with local tissue",
							"STANDARD_CONCEPT" : "S",
							"STANDARD_CONCEPT_CAPTION" : "Standard",
							"INVALID_REASON" : "V",
							"INVALID_REASON_CAPTION" : "Valid",
							"CONCEPT_CODE" : "81478009",
							"DOMAIN_ID" : "Procedure",
							"VOCABULARY_ID" : "SNOMED",
							"CONCEPT_CLASS_ID" : "Procedure"
						},
						"isExcluded" : true,
						"includeDescendants" : false,
						"includeMapped" : false
					},
					{
						"concept" : {
							"CONCEPT_ID" : 40484624,
							"CONCEPT_NAME" : "Prosthetic arthroplasty of bilateral hips",
							"STANDARD_CONCEPT" : "S",
							"STANDARD_CONCEPT_CAPTION" : "Standard",
							"INVALID_REASON" : "V",
							"INVALID_REASON_CAPTION" : "Valid",
							"CONCEPT_CODE" : "444051004",
							"DOMAIN_ID" : "Procedure",
							"VOCABULARY_ID" : "SNOMED",
							"CONCEPT_CLASS_ID" : "Procedure"
						},
						"isExcluded" : false,
						"includeDescendants" : true,
						"includeMapped" : false
					},
					{
						"concept" : {
							"CONCEPT_ID" : 4162099,
							"CONCEPT_NAME" : "Prosthetic arthroplasty of the hip",
							"STANDARD_CONCEPT" : "S",
							"STANDARD_CONCEPT_CAPTION" : "Standard",
							"INVALID_REASON" : "V",
							"INVALID_REASON_CAPTION" : "Valid",
							"CONCEPT_CODE" : "397956004",
							"DOMAIN_ID" : "Procedure",
							"VOCABULARY_ID" : "SNOMED",
							"CONCEPT_CLASS_ID" : "Procedure"
						},
						"isExcluded" : false,
						"includeDescendants" : true,
						"includeMapped" : false
					},
					{
						"concept" : {
							"CONCEPT_ID" : 37118674,
							"CONCEPT_NAME" : "Prosthetic total arthroplasty of left shoulder",
							"STANDARD_CONCEPT" : "S",
							"STANDARD_CONCEPT_CAPTION" : "Standard",
							"INVALID_REASON" : "V",
							"INVALID_REASON_CAPTION" : "Valid",
							"CONCEPT_CODE" : "733426006",
							"DOMAIN_ID" : "Procedure",
							"VOCABULARY_ID" : "SNOMED",
							"CONCEPT_CLASS_ID" : "Procedure"
						},
						"isExcluded" : false,
						"includeDescendants" : true,
						"includeMapped" : false
					},
					{
						"concept" : {
							"CONCEPT_ID" : 37116646,
							"CONCEPT_NAME" : "Prosthetic total arthroplasty of right shoulder",
							"STANDARD_CONCEPT" : "S",
							"STANDARD_CONCEPT_CAPTION" : "Standard",
							"INVALID_REASON" : "V",
							"INVALID_REASON_CAPTION" : "Valid",
							"CONCEPT_CODE" : "733429004",
							"DOMAIN_ID" : "Procedure",
							"VOCABULARY_ID" : "SNOMED",
							"CONCEPT_CLASS_ID" : "Procedure"
						},
						"isExcluded" : false,
						"includeDescendants" : true,
						"includeMapped" : false
					},
					{
						"concept" : {
							"CONCEPT_ID" : 4034299,
							"CONCEPT_NAME" : "Prosthetic unicompartmental arthroplasty of knee",
							"STANDARD_CONCEPT" : "S",
							"STANDARD_CONCEPT_CAPTION" : "Standard",
							"INVALID_REASON" : "V",
							"INVALID_REASON_CAPTION" : "Valid",
							"CONCEPT_CODE" : "239501000",
							"DOMAIN_ID" : "Procedure",
							"VOCABULARY_ID" : "SNOMED",
							"CONCEPT_CLASS_ID" : "Procedure"
						},
						"isExcluded" : false,
						"includeDescendants" : true,
						"includeMapped" : false
					},
					{
						"concept" : {
							"CONCEPT_ID" : 4205774,
							"CONCEPT_NAME" : "Reconstruction of dislocating patella with patellectomy",
							"STANDARD_CONCEPT" : "S",
							"STANDARD_CONCEPT_CAPTION" : "Standard",
							"INVALID_REASON" : "V",
							"INVALID_REASON_CAPTION" : "Valid",
							"CONCEPT_CODE" : "438562002",
							"DOMAIN_ID" : "Procedure",
							"VOCABULARY_ID" : "SNOMED",
							"CONCEPT_CLASS_ID" : "Procedure"
						},
						"isExcluded" : true,
						"includeDescendants" : false,
						"includeMapped" : false
					},
					{
						"concept" : {
							"CONCEPT_ID" : 37017415,
							"CONCEPT_NAME" : "Reconstruction of joint of knee with external fixation",
							"STANDARD_CONCEPT" : "S",
							"STANDARD_CONCEPT_CAPTION" : "Standard",
							"INVALID_REASON" : "V",
							"INVALID_REASON_CAPTION" : "Valid",
							"CONCEPT_CODE" : "713685008",
							"DOMAIN_ID" : "Procedure",
							"VOCABULARY_ID" : "SNOMED",
							"CONCEPT_CLASS_ID" : "Procedure"
						},
						"isExcluded" : true,
						"includeDescendants" : false,
						"includeMapped" : false
					},
					{
						"concept" : {
							"CONCEPT_ID" : 44807384,
							"CONCEPT_NAME" : "Reconstruction of medial patellofemoral ligament",
							"STANDARD_CONCEPT" : "S",
							"STANDARD_CONCEPT_CAPTION" : "Standard",
							"INVALID_REASON" : "V",
							"INVALID_REASON_CAPTION" : "Valid",
							"CONCEPT_CODE" : "816611000000105",
							"DOMAIN_ID" : "Procedure",
							"VOCABULARY_ID" : "SNOMED",
							"CONCEPT_CLASS_ID" : "Procedure"
						},
						"isExcluded" : true,
						"includeDescendants" : false,
						"includeMapped" : false
					},
					{
						"concept" : {
							"CONCEPT_ID" : 4346964,
							"CONCEPT_NAME" : "Reconstruction of posterior cruciate ligament of knee joint",
							"STANDARD_CONCEPT" : "S",
							"STANDARD_CONCEPT_CAPTION" : "Standard",
							"INVALID_REASON" : "V",
							"INVALID_REASON_CAPTION" : "Valid",
							"CONCEPT_CODE" : "239432002",
							"DOMAIN_ID" : "Procedure",
							"VOCABULARY_ID" : "SNOMED",
							"CONCEPT_CLASS_ID" : "Procedure"
						},
						"isExcluded" : true,
						"includeDescendants" : false,
						"includeMapped" : false
					},
					{
						"concept" : {
							"CONCEPT_ID" : 2104592,
							"CONCEPT_NAME" : "Reconstruction, collateral ligament, interphalangeal joint, single, including graft, each joint",
							"STANDARD_CONCEPT" : "S",
							"STANDARD_CONCEPT_CAPTION" : "Standard",
							"INVALID_REASON" : "V",
							"INVALID_REASON_CAPTION" : "Valid",
							"CONCEPT_CODE" : "26545",
							"DOMAIN_ID" : "Procedure",
							"VOCABULARY_ID" : "CPT4",
							"CONCEPT_CLASS_ID" : "CPT4"
						},
						"isExcluded" : true,
						"includeDescendants" : false,
						"includeMapped" : false
					},
					{
						"concept" : {
							"CONCEPT_ID" : 2104581,
							"CONCEPT_NAME" : "Reconstruction, collateral ligament, metacarpophalangeal joint, single; with local tissue (eg, adductor advancement)",
							"STANDARD_CONCEPT" : "S",
							"STANDARD_CONCEPT_CAPTION" : "Standard",
							"INVALID_REASON" : "V",
							"INVALID_REASON_CAPTION" : "Valid",
							"CONCEPT_CODE" : "26542",
							"DOMAIN_ID" : "Procedure",
							"VOCABULARY_ID" : "CPT4",
							"CONCEPT_CLASS_ID" : "CPT4"
						},
						"isExcluded" : true,
						"includeDescendants" : false,
						"includeMapped" : false
					},
					{
						"concept" : {
							"CONCEPT_ID" : 2104580,
							"CONCEPT_NAME" : "Reconstruction, collateral ligament, metacarpophalangeal joint, single; with tendon or fascial graft (includes obtaining graft)",
							"STANDARD_CONCEPT" : "S",
							"STANDARD_CONCEPT_CAPTION" : "Standard",
							"INVALID_REASON" : "V",
							"INVALID_REASON_CAPTION" : "Valid",
							"CONCEPT_CODE" : "26541",
							"DOMAIN_ID" : "Procedure",
							"VOCABULARY_ID" : "CPT4",
							"CONCEPT_CLASS_ID" : "CPT4"
						},
						"isExcluded" : true,
						"includeDescendants" : false,
						"includeMapped" : false
					},
					{
						"concept" : {
							"CONCEPT_ID" : 2104594,
							"CONCEPT_NAME" : "Repair and reconstruction, finger, volar plate, interphalangeal joint",
							"STANDARD_CONCEPT" : "S",
							"STANDARD_CONCEPT_CAPTION" : "Standard",
							"INVALID_REASON" : "V",
							"INVALID_REASON_CAPTION" : "Valid",
							"CONCEPT_CODE" : "26548",
							"DOMAIN_ID" : "Procedure",
							"VOCABULARY_ID" : "CPT4",
							"CONCEPT_CLASS_ID" : "CPT4"
						},
						"isExcluded" : true,
						"includeDescendants" : false,
						"includeMapped" : false
					},
					{
						"concept" : {
							"CONCEPT_ID" : 2104579,
							"CONCEPT_NAME" : "Repair of collateral ligament, metacarpophalangeal or interphalangeal joint",
							"STANDARD_CONCEPT" : "S",
							"STANDARD_CONCEPT_CAPTION" : "Standard",
							"INVALID_REASON" : "V",
							"INVALID_REASON_CAPTION" : "Valid",
							"CONCEPT_CODE" : "26540",
							"DOMAIN_ID" : "Procedure",
							"VOCABULARY_ID" : "CPT4",
							"CONCEPT_CLASS_ID" : "CPT4"
						},
						"isExcluded" : true,
						"includeDescendants" : false,
						"includeMapped" : false
					},
					{
						"concept" : {
							"CONCEPT_ID" : 4133304,
							"CONCEPT_NAME" : "Repair of joint capsule of knee",
							"STANDARD_CONCEPT" : "S",
							"STANDARD_CONCEPT_CAPTION" : "Standard",
							"INVALID_REASON" : "V",
							"INVALID_REASON_CAPTION" : "Valid",
							"CONCEPT_CODE" : "127598004",
							"DOMAIN_ID" : "Procedure",
							"VOCABULARY_ID" : "SNOMED",
							"CONCEPT_CLASS_ID" : "Procedure"
						},
						"isExcluded" : true,
						"includeDescendants" : false,
						"includeMapped" : false
					},
					{
						"concept" : {
							"CONCEPT_ID" : 4147773,
							"CONCEPT_NAME" : "Repair of knee cruciate ligaments",
							"STANDARD_CONCEPT" : "S",
							"STANDARD_CONCEPT_CAPTION" : "Standard",
							"INVALID_REASON" : "V",
							"INVALID_REASON_CAPTION" : "Valid",
							"CONCEPT_CODE" : "35926005",
							"DOMAIN_ID" : "Procedure",
							"VOCABULARY_ID" : "SNOMED",
							"CONCEPT_CLASS_ID" : "Procedure"
						},
						"isExcluded" : true,
						"includeDescendants" : false,
						"includeMapped" : false
					},
					{
						"concept" : {
							"CONCEPT_ID" : 4072040,
							"CONCEPT_NAME" : "Repair of patellar tendon",
							"STANDARD_CONCEPT" : "S",
							"STANDARD_CONCEPT_CAPTION" : "Standard",
							"INVALID_REASON" : "V",
							"INVALID_REASON_CAPTION" : "Valid",
							"CONCEPT_CODE" : "178158006",
							"DOMAIN_ID" : "Procedure",
							"VOCABULARY_ID" : "SNOMED",
							"CONCEPT_CLASS_ID" : "Procedure"
						},
						"isExcluded" : true,
						"includeDescendants" : false,
						"includeMapped" : false
					},
					{
						"concept" : {
							"CONCEPT_ID" : 4343906,
							"CONCEPT_NAME" : "Repair of ulnar collateral ligament of metacarpophalangeal joint of thumb",
							"STANDARD_CONCEPT" : "S",
							"STANDARD_CONCEPT_CAPTION" : "Standard",
							"INVALID_REASON" : "V",
							"INVALID_REASON_CAPTION" : "Valid",
							"CONCEPT_CODE" : "239424005",
							"DOMAIN_ID" : "Procedure",
							"VOCABULARY_ID" : "SNOMED",
							"CONCEPT_CLASS_ID" : "Procedure"
						},
						"isExcluded" : true,
						"includeDescendants" : false,
						"includeMapped" : false
					},
					{
						"concept" : {
							"CONCEPT_ID" : 40486115,
							"CONCEPT_NAME" : "Suturing of capsule of metacarpophalangeal joint",
							"STANDARD_CONCEPT" : "S",
							"STANDARD_CONCEPT_CAPTION" : "Standard",
							"INVALID_REASON" : "V",
							"INVALID_REASON_CAPTION" : "Valid",
							"CONCEPT_CODE" : "447735009",
							"DOMAIN_ID" : "Procedure",
							"VOCABULARY_ID" : "SNOMED",
							"CONCEPT_CLASS_ID" : "Procedure"
						},
						"isExcluded" : true,
						"includeDescendants" : false,
						"includeMapped" : false
					},
					{
						"concept" : {
							"CONCEPT_ID" : 40488023,
							"CONCEPT_NAME" : "Suturing of ligament of interphalangeal joint of hand",
							"STANDARD_CONCEPT" : "S",
							"STANDARD_CONCEPT_CAPTION" : "Standard",
							"INVALID_REASON" : "V",
							"INVALID_REASON_CAPTION" : "Valid",
							"CONCEPT_CODE" : "448112002",
							"DOMAIN_ID" : "Procedure",
							"VOCABULARY_ID" : "SNOMED",
							"CONCEPT_CLASS_ID" : "Procedure"
						},
						"isExcluded" : true,
						"includeDescendants" : false,
						"includeMapped" : false
					},
					{
						"concept" : {
							"CONCEPT_ID" : 40488022,
							"CONCEPT_NAME" : "Suturing of ligament of metacarpophalangeal joint",
							"STANDARD_CONCEPT" : "S",
							"STANDARD_CONCEPT_CAPTION" : "Standard",
							"INVALID_REASON" : "V",
							"INVALID_REASON_CAPTION" : "Valid",
							"CONCEPT_CODE" : "448111009",
							"DOMAIN_ID" : "Procedure",
							"VOCABULARY_ID" : "SNOMED",
							"CONCEPT_CLASS_ID" : "Procedure"
						},
						"isExcluded" : true,
						"includeDescendants" : false,
						"includeMapped" : false
					},
					{
						"concept" : {
							"CONCEPT_ID" : 4153680,
							"CONCEPT_NAME" : "Tibial plateau leveling operation",
							"STANDARD_CONCEPT" : "S",
							"STANDARD_CONCEPT_CAPTION" : "Standard",
							"INVALID_REASON" : "V",
							"INVALID_REASON_CAPTION" : "Valid",
							"CONCEPT_CODE" : "370613001",
							"DOMAIN_ID" : "Procedure",
							"VOCABULARY_ID" : "SNOMED",
							"CONCEPT_CLASS_ID" : "Procedure"
						},
						"isExcluded" : true,
						"includeDescendants" : false,
						"includeMapped" : false
					},
					{
						"concept" : {
							"CONCEPT_ID" : 4203771,
							"CONCEPT_NAME" : "Total replacement of hip",
							"STANDARD_CONCEPT" : "S",
							"STANDARD_CONCEPT_CAPTION" : "Standard",
							"INVALID_REASON" : "V",
							"INVALID_REASON_CAPTION" : "Valid",
							"CONCEPT_CODE" : "52734007",
							"DOMAIN_ID" : "Procedure",
							"VOCABULARY_ID" : "SNOMED",
							"CONCEPT_CLASS_ID" : "Procedure"
						},
						"isExcluded" : false,
						"includeDescendants" : true,
						"includeMapped" : false
					},
					{
						"concept" : {
							"CONCEPT_ID" : 4343701,
							"CONCEPT_NAME" : "Transfer of patellar tendon",
							"STANDARD_CONCEPT" : "S",
							"STANDARD_CONCEPT_CAPTION" : "Standard",
							"INVALID_REASON" : "V",
							"INVALID_REASON_CAPTION" : "Valid",
							"CONCEPT_CODE" : "239245001",
							"DOMAIN_ID" : "Procedure",
							"VOCABULARY_ID" : "SNOMED",
							"CONCEPT_CLASS_ID" : "Procedure"
						},
						"isExcluded" : true,
						"includeDescendants" : false,
						"includeMapped" : false
					},
					{
						"concept" : {
							"CONCEPT_ID" : 4002021,
							"CONCEPT_NAME" : "Triad knee repair",
							"STANDARD_CONCEPT" : "S",
							"STANDARD_CONCEPT_CAPTION" : "Standard",
							"INVALID_REASON" : "V",
							"INVALID_REASON_CAPTION" : "Valid",
							"CONCEPT_CODE" : "1104006",
							"DOMAIN_ID" : "Procedure",
							"VOCABULARY_ID" : "SNOMED",
							"CONCEPT_CLASS_ID" : "Procedure"
						},
						"isExcluded" : true,
						"includeDescendants" : false,
						"includeMapped" : false
					}
				]
			}
		},
		{
			"id" : 34,
			"name" : "[MSK_AI]outcome_oa_all_combined - OPTIMIZED",
			"expression" : {
				"items" : [
					{
						"concept" : {
							"CONCEPT_ID" : 4002683,
							"CONCEPT_NAME" : "Acute calcific periarthritis",
							"STANDARD_CONCEPT" : "S",
							"STANDARD_CONCEPT_CAPTION" : "Standard",
							"INVALID_REASON" : "V",
							"INVALID_REASON_CAPTION" : "Valid",
							"CONCEPT_CODE" : "11023001",
							"DOMAIN_ID" : "Condition",
							"VOCABULARY_ID" : "SNOMED",
							"CONCEPT_CLASS_ID" : "Clinical Finding"
						},
						"isExcluded" : true,
						"includeDescendants" : false,
						"includeMapped" : false
					},
					{
						"concept" : {
							"CONCEPT_ID" : 35208766,
							"CONCEPT_NAME" : "Bilateral primary osteoarthritis of hip",
							"STANDARD_CONCEPT" : "N",
							"STANDARD_CONCEPT_CAPTION" : "Non-Standard",
							"INVALID_REASON" : "V",
							"INVALID_REASON_CAPTION" : "Valid",
							"CONCEPT_CODE" : "M16.0",
							"DOMAIN_ID" : "Condition",
							"VOCABULARY_ID" : "ICD10CM",
							"CONCEPT_CLASS_ID" : "4-char billing code"
						},
						"isExcluded" : false,
						"includeDescendants" : true,
						"includeMapped" : false
					},
					{
						"concept" : {
							"CONCEPT_ID" : 36687025,
							"CONCEPT_NAME" : "Chondrocalcinosis of bilateral hips",
							"STANDARD_CONCEPT" : "S",
							"STANDARD_CONCEPT_CAPTION" : "Standard",
							"INVALID_REASON" : "V",
							"INVALID_REASON_CAPTION" : "Valid",
							"CONCEPT_CODE" : "15705361000119101",
							"DOMAIN_ID" : "Condition",
							"VOCABULARY_ID" : "SNOMED",
							"CONCEPT_CLASS_ID" : "Clinical Finding"
						},
						"isExcluded" : true,
						"includeDescendants" : false,
						"includeMapped" : false
					},
					{
						"concept" : {
							"CONCEPT_ID" : 40479260,
							"CONCEPT_NAME" : "Chondrocalcinosis of knee joint",
							"STANDARD_CONCEPT" : "S",
							"STANDARD_CONCEPT_CAPTION" : "Standard",
							"INVALID_REASON" : "V",
							"INVALID_REASON_CAPTION" : "Valid",
							"CONCEPT_CODE" : "442942009",
							"DOMAIN_ID" : "Condition",
							"VOCABULARY_ID" : "SNOMED",
							"CONCEPT_CLASS_ID" : "Clinical Finding"
						},
						"isExcluded" : true,
						"includeDescendants" : false,
						"includeMapped" : false
					},
					{
						"concept" : {
							"CONCEPT_ID" : 36717013,
							"CONCEPT_NAME" : "Chondromalacia of right patella",
							"STANDARD_CONCEPT" : "S",
							"STANDARD_CONCEPT_CAPTION" : "Standard",
							"INVALID_REASON" : "V",
							"INVALID_REASON_CAPTION" : "Valid",
							"CONCEPT_CODE" : "15749161000119108",
							"DOMAIN_ID" : "Condition",
							"VOCABULARY_ID" : "SNOMED",
							"CONCEPT_CLASS_ID" : "Clinical Finding"
						},
						"isExcluded" : true,
						"includeDescendants" : false,
						"includeMapped" : false
					},
					{
						"concept" : {
							"CONCEPT_ID" : 762219,
							"CONCEPT_NAME" : "Chronic tophaceous gout of right wrist due to renal impairment",
							"STANDARD_CONCEPT" : "S",
							"STANDARD_CONCEPT_CAPTION" : "Standard",
							"INVALID_REASON" : "V",
							"INVALID_REASON_CAPTION" : "Valid",
							"CONCEPT_CODE" : "304261000119109",
							"DOMAIN_ID" : "Condition",
							"VOCABULARY_ID" : "SNOMED",
							"CONCEPT_CLASS_ID" : "Clinical Finding"
						},
						"isExcluded" : true,
						"includeDescendants" : false,
						"includeMapped" : false
					},
					{
						"concept" : {
							"CONCEPT_ID" : 4003507,
							"CONCEPT_NAME" : "Degenerative arthritis of temporomandibular joint",
							"STANDARD_CONCEPT" : "S",
							"STANDARD_CONCEPT_CAPTION" : "Standard",
							"INVALID_REASON" : "V",
							"INVALID_REASON_CAPTION" : "Valid",
							"CONCEPT_CODE" : "109668000",
							"DOMAIN_ID" : "Condition",
							"VOCABULARY_ID" : "SNOMED",
							"CONCEPT_CLASS_ID" : "Clinical Finding"
						},
						"isExcluded" : true,
						"includeDescendants" : false,
						"includeMapped" : false
					},
					{
						"concept" : {
							"CONCEPT_ID" : 37111597,
							"CONCEPT_NAME" : "Familial chondromalacia patellae",
							"STANDARD_CONCEPT" : "S",
							"STANDARD_CONCEPT_CAPTION" : "Standard",
							"INVALID_REASON" : "V",
							"INVALID_REASON_CAPTION" : "Valid",
							"CONCEPT_CODE" : "726628003",
							"DOMAIN_ID" : "Condition",
							"VOCABULARY_ID" : "SNOMED",
							"CONCEPT_CLASS_ID" : "Clinical Finding"
						},
						"isExcluded" : true,
						"includeDescendants" : false,
						"includeMapped" : false
					},
					{
						"concept" : {
							"CONCEPT_ID" : 45437062,
							"CONCEPT_NAME" : "Hip osteoarthritis NOS",
							"STANDARD_CONCEPT" : "N",
							"STANDARD_CONCEPT_CAPTION" : "Non-Standard",
							"INVALID_REASON" : "V",
							"INVALID_REASON_CAPTION" : "Valid",
							"CONCEPT_CODE" : "N05z511",
							"DOMAIN_ID" : "Condition",
							"VOCABULARY_ID" : "Read",
							"CONCEPT_CLASS_ID" : "Read"
						},
						"isExcluded" : false,
						"includeDescendants" : true,
						"includeMapped" : false
					},
					{
						"concept" : {
							"CONCEPT_ID" : 762775,
							"CONCEPT_NAME" : "Intervertebral disc desiccation",
							"STANDARD_CONCEPT" : "S",
							"STANDARD_CONCEPT_CAPTION" : "Standard",
							"INVALID_REASON" : "V",
							"INVALID_REASON_CAPTION" : "Valid",
							"CONCEPT_CODE" : "431731000124106",
							"DOMAIN_ID" : "Condition",
							"VOCABULARY_ID" : "SNOMED",
							"CONCEPT_CLASS_ID" : "Clinical Finding"
						},
						"isExcluded" : true,
						"includeDescendants" : false,
						"includeMapped" : false
					},
					{
						"concept" : {
							"CONCEPT_ID" : 4344390,
							"CONCEPT_NAME" : "Intervertebral disk calcification",
							"STANDARD_CONCEPT" : "S",
							"STANDARD_CONCEPT_CAPTION" : "Standard",
							"INVALID_REASON" : "V",
							"INVALID_REASON_CAPTION" : "Valid",
							"CONCEPT_CODE" : "240211000",
							"DOMAIN_ID" : "Condition",
							"VOCABULARY_ID" : "SNOMED",
							"CONCEPT_CLASS_ID" : "Clinical Finding"
						},
						"isExcluded" : true,
						"includeDescendants" : false,
						"includeMapped" : false
					},
					{
						"concept" : {
							"CONCEPT_ID" : 4083689,
							"CONCEPT_NAME" : "Intra-articular steroid-induced arthritis and periarthritis",
							"STANDARD_CONCEPT" : "S",
							"STANDARD_CONCEPT_CAPTION" : "Standard",
							"INVALID_REASON" : "V",
							"INVALID_REASON_CAPTION" : "Valid",
							"CONCEPT_CODE" : "239849004",
							"DOMAIN_ID" : "Condition",
							"VOCABULARY_ID" : "SNOMED",
							"CONCEPT_CLASS_ID" : "Clinical Finding"
						},
						"isExcluded" : true,
						"includeDescendants" : false,
						"includeMapped" : false
					},
					{
						"concept" : {
							"CONCEPT_ID" : 45453633,
							"CONCEPT_NAME" : "Localised osteoarthritis, unspecified, of the pelvic region and thigh",
							"STANDARD_CONCEPT" : "N",
							"STANDARD_CONCEPT_CAPTION" : "Non-Standard",
							"INVALID_REASON" : "V",
							"INVALID_REASON_CAPTION" : "Valid",
							"CONCEPT_CODE" : "N053500",
							"DOMAIN_ID" : "Condition",
							"VOCABULARY_ID" : "Read",
							"CONCEPT_CLASS_ID" : "Read"
						},
						"isExcluded" : false,
						"includeDescendants" : true,
						"includeMapped" : false
					},
					{
						"concept" : {
							"CONCEPT_ID" : 45490472,
							"CONCEPT_NAME" : "Localised, primary osteoarthritis of the pelvic region and thigh",
							"STANDARD_CONCEPT" : "N",
							"STANDARD_CONCEPT_CAPTION" : "Non-Standard",
							"INVALID_REASON" : "V",
							"INVALID_REASON_CAPTION" : "Valid",
							"CONCEPT_CODE" : "N051500",
							"DOMAIN_ID" : "Condition",
							"VOCABULARY_ID" : "Read",
							"CONCEPT_CLASS_ID" : "Read"
						},
						"isExcluded" : false,
						"includeDescendants" : true,
						"includeMapped" : false
					},
					{
						"concept" : {
							"CONCEPT_ID" : 45443644,
							"CONCEPT_NAME" : "Localised, secondary osteoarthritis of the pelvic region and thigh",
							"STANDARD_CONCEPT" : "N",
							"STANDARD_CONCEPT_CAPTION" : "Non-Standard",
							"INVALID_REASON" : "V",
							"INVALID_REASON_CAPTION" : "Valid",
							"CONCEPT_CODE" : "N052500",
							"DOMAIN_ID" : "Condition",
							"VOCABULARY_ID" : "Read",
							"CONCEPT_CLASS_ID" : "Read"
						},
						"isExcluded" : true,
						"includeDescendants" : false,
						"includeMapped" : false
					},
					{
						"concept" : {
							"CONCEPT_ID" : 80802,
							"CONCEPT_NAME" : "Localized, secondary osteoarthritis",
							"STANDARD_CONCEPT" : "S",
							"STANDARD_CONCEPT_CAPTION" : "Standard",
							"INVALID_REASON" : "V",
							"INVALID_REASON_CAPTION" : "Valid",
							"CONCEPT_CODE" : "201847001",
							"DOMAIN_ID" : "Condition",
							"VOCABULARY_ID" : "SNOMED",
							"CONCEPT_CLASS_ID" : "Clinical Finding"
						},
						"isExcluded" : true,
						"includeDescendants" : false,
						"includeMapped" : false
					},
					{
						"concept" : {
							"CONCEPT_ID" : 80183,
							"CONCEPT_NAME" : "Localized, secondary osteoarthritis of the ankle and/or foot",
							"STANDARD_CONCEPT" : "S",
							"STANDARD_CONCEPT_CAPTION" : "Standard",
							"INVALID_REASON" : "V",
							"INVALID_REASON_CAPTION" : "Valid",
							"CONCEPT_CODE" : "201855008",
							"DOMAIN_ID" : "Condition",
							"VOCABULARY_ID" : "SNOMED",
							"CONCEPT_CLASS_ID" : "Clinical Finding"
						},
						"isExcluded" : true,
						"includeDescendants" : false,
						"includeMapped" : false
					},
					{
						"concept" : {
							"CONCEPT_ID" : 79904,
							"CONCEPT_NAME" : "Localized, secondary osteoarthritis of the hand",
							"STANDARD_CONCEPT" : "S",
							"STANDARD_CONCEPT_CAPTION" : "Standard",
							"INVALID_REASON" : "V",
							"INVALID_REASON_CAPTION" : "Valid",
							"CONCEPT_CODE" : "201852006",
							"DOMAIN_ID" : "Condition",
							"VOCABULARY_ID" : "SNOMED",
							"CONCEPT_CLASS_ID" : "Clinical Finding"
						},
						"isExcluded" : true,
						"includeDescendants" : false,
						"includeMapped" : false
					},
					{
						"concept" : {
							"CONCEPT_ID" : 4150309,
							"CONCEPT_NAME" : "Localized, secondary osteoarthritis of the pelvic region and thigh",
							"STANDARD_CONCEPT" : "S",
							"STANDARD_CONCEPT_CAPTION" : "Standard",
							"INVALID_REASON" : "V",
							"INVALID_REASON_CAPTION" : "Valid",
							"CONCEPT_CODE" : "267890003",
							"DOMAIN_ID" : "Condition",
							"VOCABULARY_ID" : "SNOMED",
							"CONCEPT_CLASS_ID" : "Clinical Finding"
						},
						"isExcluded" : true,
						"includeDescendants" : false,
						"includeMapped" : false
					},
					{
						"concept" : {
							"CONCEPT_ID" : 77631,
							"CONCEPT_NAME" : "Localized, secondary osteoarthritis of the shoulder region",
							"STANDARD_CONCEPT" : "S",
							"STANDARD_CONCEPT_CAPTION" : "Standard",
							"INVALID_REASON" : "V",
							"INVALID_REASON_CAPTION" : "Valid",
							"CONCEPT_CODE" : "201849003",
							"DOMAIN_ID" : "Condition",
							"VOCABULARY_ID" : "SNOMED",
							"CONCEPT_CLASS_ID" : "Clinical Finding"
						},
						"isExcluded" : true,
						"includeDescendants" : false,
						"includeMapped" : false
					},
					{
						"concept" : {
							"CONCEPT_ID" : 4178758,
							"CONCEPT_NAME" : "Miner's knee",
							"STANDARD_CONCEPT" : "S",
							"STANDARD_CONCEPT_CAPTION" : "Standard",
							"INVALID_REASON" : "V",
							"INVALID_REASON_CAPTION" : "Valid",
							"CONCEPT_CODE" : "52334005",
							"DOMAIN_ID" : "Condition",
							"VOCABULARY_ID" : "SNOMED",
							"CONCEPT_CLASS_ID" : "Clinical Finding"
						},
						"isExcluded" : true,
						"includeDescendants" : false,
						"includeMapped" : false
					},
					{
						"concept" : {
							"CONCEPT_ID" : 45527231,
							"CONCEPT_NAME" : "OSTEOARTHRITIS HIP",
							"STANDARD_CONCEPT" : "N",
							"STANDARD_CONCEPT_CAPTION" : "Non-Standard",
							"INVALID_REASON" : "V",
							"INVALID_REASON_CAPTION" : "Valid",
							"CONCEPT_CODE" : "7130DA",
							"DOMAIN_ID" : "Condition",
							"VOCABULARY_ID" : "OXMIS",
							"CONCEPT_CLASS_ID" : "OXMIS"
						},
						"isExcluded" : false,
						"includeDescendants" : true,
						"includeMapped" : false
					},
					{
						"concept" : {
							"CONCEPT_ID" : 45450329,
							"CONCEPT_NAME" : "Oligoarticular osteoarthritis, unspecified, of the pelvic region and thigh",
							"STANDARD_CONCEPT" : "N",
							"STANDARD_CONCEPT_CAPTION" : "Non-Standard",
							"INVALID_REASON" : "V",
							"INVALID_REASON_CAPTION" : "Valid",
							"CONCEPT_CODE" : "N054500",
							"DOMAIN_ID" : "Condition",
							"VOCABULARY_ID" : "Read",
							"CONCEPT_CLASS_ID" : "Read"
						},
						"isExcluded" : false,
						"includeDescendants" : true,
						"includeMapped" : false
					},
					{
						"concept" : {
							"CONCEPT_ID" : 80180,
							"CONCEPT_NAME" : "Osteoarthritis",
							"STANDARD_CONCEPT" : "S",
							"STANDARD_CONCEPT_CAPTION" : "Standard",
							"INVALID_REASON" : "V",
							"INVALID_REASON_CAPTION" : "Valid",
							"CONCEPT_CODE" : "396275006",
							"DOMAIN_ID" : "Condition",
							"VOCABULARY_ID" : "SNOMED",
							"CONCEPT_CLASS_ID" : "Clinical Finding"
						},
						"isExcluded" : false,
						"includeDescendants" : true,
						"includeMapped" : false
					},
					{
						"concept" : {
							"CONCEPT_ID" : 45443649,
							"CONCEPT_NAME" : "Osteoarthritis NOS, of hip",
							"STANDARD_CONCEPT" : "N",
							"STANDARD_CONCEPT_CAPTION" : "Non-Standard",
							"INVALID_REASON" : "V",
							"INVALID_REASON_CAPTION" : "Valid",
							"CONCEPT_CODE" : "N05zJ00",
							"DOMAIN_ID" : "Condition",
							"VOCABULARY_ID" : "Read",
							"CONCEPT_CLASS_ID" : "Read"
						},
						"isExcluded" : false,
						"includeDescendants" : true,
						"includeMapped" : false
					},
					{
						"concept" : {
							"CONCEPT_ID" : 45470615,
							"CONCEPT_NAME" : "Osteoarthritis NOS, pelvic region/thigh",
							"STANDARD_CONCEPT" : "N",
							"STANDARD_CONCEPT_CAPTION" : "Non-Standard",
							"INVALID_REASON" : "V",
							"INVALID_REASON_CAPTION" : "Valid",
							"CONCEPT_CODE" : "N05z500",
							"DOMAIN_ID" : "Condition",
							"VOCABULARY_ID" : "Read",
							"CONCEPT_CLASS_ID" : "Read"
						},
						"isExcluded" : false,
						"includeDescendants" : true,
						"includeMapped" : false
					},
					{
						"concept" : {
							"CONCEPT_ID" : 1570329,
							"CONCEPT_NAME" : "Osteoarthritis of hip",
							"STANDARD_CONCEPT" : "N",
							"STANDARD_CONCEPT_CAPTION" : "Non-Standard",
							"INVALID_REASON" : "V",
							"INVALID_REASON_CAPTION" : "Valid",
							"CONCEPT_CODE" : "M16",
							"DOMAIN_ID" : "Condition",
							"VOCABULARY_ID" : "ICD10CM",
							"CONCEPT_CLASS_ID" : "3-char nonbill code"
						},
						"isExcluded" : false,
						"includeDescendants" : true,
						"includeMapped" : false
					},
					{
						"concept" : {
							"CONCEPT_ID" : 35208771,
							"CONCEPT_NAME" : "Osteoarthritis of hip, unspecified",
							"STANDARD_CONCEPT" : "N",
							"STANDARD_CONCEPT_CAPTION" : "Non-Standard",
							"INVALID_REASON" : "V",
							"INVALID_REASON_CAPTION" : "Valid",
							"CONCEPT_CODE" : "M16.9",
							"DOMAIN_ID" : "Condition",
							"VOCABULARY_ID" : "ICD10CM",
							"CONCEPT_CLASS_ID" : "4-char billing code"
						},
						"isExcluded" : false,
						"includeDescendants" : true,
						"includeMapped" : false
					},
					{
						"concept" : {
							"CONCEPT_ID" : 35208769,
							"CONCEPT_NAME" : "Other bilateral secondary osteoarthritis of hip",
							"STANDARD_CONCEPT" : "N",
							"STANDARD_CONCEPT_CAPTION" : "Non-Standard",
							"INVALID_REASON" : "V",
							"INVALID_REASON_CAPTION" : "Valid",
							"CONCEPT_CODE" : "M16.6",
							"DOMAIN_ID" : "Condition",
							"VOCABULARY_ID" : "ICD10CM",
							"CONCEPT_CLASS_ID" : "4-char billing code"
						},
						"isExcluded" : false,
						"includeDescendants" : true,
						"includeMapped" : false
					},
					{
						"concept" : {
							"CONCEPT_ID" : 35208770,
							"CONCEPT_NAME" : "Other unilateral secondary osteoarthritis of hip",
							"STANDARD_CONCEPT" : "N",
							"STANDARD_CONCEPT_CAPTION" : "Non-Standard",
							"INVALID_REASON" : "V",
							"INVALID_REASON_CAPTION" : "Valid",
							"CONCEPT_CODE" : "M16.7",
							"DOMAIN_ID" : "Condition",
							"VOCABULARY_ID" : "ICD10CM",
							"CONCEPT_CLASS_ID" : "4-char billing code"
						},
						"isExcluded" : false,
						"includeDescendants" : true,
						"includeMapped" : false
					},
					{
						"concept" : {
							"CONCEPT_ID" : 4264472,
							"CONCEPT_NAME" : "Pellegrini-Stieda syndrome",
							"STANDARD_CONCEPT" : "S",
							"STANDARD_CONCEPT_CAPTION" : "Standard",
							"INVALID_REASON" : "V",
							"INVALID_REASON_CAPTION" : "Valid",
							"CONCEPT_CODE" : "60644007",
							"DOMAIN_ID" : "Condition",
							"VOCABULARY_ID" : "SNOMED",
							"CONCEPT_CLASS_ID" : "Clinical Finding"
						},
						"isExcluded" : true,
						"includeDescendants" : false,
						"includeMapped" : false
					},
					{
						"concept" : {
							"CONCEPT_ID" : 4029605,
							"CONCEPT_NAME" : "Periarticular calcification",
							"STANDARD_CONCEPT" : "S",
							"STANDARD_CONCEPT_CAPTION" : "Standard",
							"INVALID_REASON" : "V",
							"INVALID_REASON_CAPTION" : "Valid",
							"CONCEPT_CODE" : "237898004",
							"DOMAIN_ID" : "Condition",
							"VOCABULARY_ID" : "SNOMED",
							"CONCEPT_CLASS_ID" : "Clinical Finding"
						},
						"isExcluded" : true,
						"includeDescendants" : false,
						"includeMapped" : false
					},
					{
						"concept" : {
							"CONCEPT_ID" : 4216873,
							"CONCEPT_NAME" : "Relapsing polychondritis",
							"STANDARD_CONCEPT" : "S",
							"STANDARD_CONCEPT_CAPTION" : "Standard",
							"INVALID_REASON" : "V",
							"INVALID_REASON_CAPTION" : "Valid",
							"CONCEPT_CODE" : "72275000",
							"DOMAIN_ID" : "Condition",
							"VOCABULARY_ID" : "SNOMED",
							"CONCEPT_CLASS_ID" : "Clinical Finding"
						},
						"isExcluded" : true,
						"includeDescendants" : false,
						"includeMapped" : false
					},
					{
						"concept" : {
							"CONCEPT_ID" : 4215655,
							"CONCEPT_NAME" : "Tibial plateau chondromalacia",
							"STANDARD_CONCEPT" : "S",
							"STANDARD_CONCEPT_CAPTION" : "Standard",
							"INVALID_REASON" : "V",
							"INVALID_REASON_CAPTION" : "Valid",
							"CONCEPT_CODE" : "4168008",
							"DOMAIN_ID" : "Condition",
							"VOCABULARY_ID" : "SNOMED",
							"CONCEPT_CLASS_ID" : "Clinical Finding"
						},
						"isExcluded" : true,
						"includeDescendants" : false,
						"includeMapped" : false
					},
					{
						"concept" : {
							"CONCEPT_ID" : 1570330,
							"CONCEPT_NAME" : "Unilateral primary osteoarthritis of hip",
							"STANDARD_CONCEPT" : "N",
							"STANDARD_CONCEPT_CAPTION" : "Non-Standard",
							"INVALID_REASON" : "V",
							"INVALID_REASON_CAPTION" : "Valid",
							"CONCEPT_CODE" : "M16.1",
							"DOMAIN_ID" : "Condition",
							"VOCABULARY_ID" : "ICD10CM",
							"CONCEPT_CLASS_ID" : "4-char nonbill code"
						},
						"isExcluded" : false,
						"includeDescendants" : true,
						"includeMapped" : false
					},
					{
						"concept" : {
							"CONCEPT_ID" : 45577164,
							"CONCEPT_NAME" : "Unilateral primary osteoarthritis, left hip",
							"STANDARD_CONCEPT" : "N",
							"STANDARD_CONCEPT_CAPTION" : "Non-Standard",
							"INVALID_REASON" : "V",
							"INVALID_REASON_CAPTION" : "Valid",
							"CONCEPT_CODE" : "M16.12",
							"DOMAIN_ID" : "Condition",
							"VOCABULARY_ID" : "ICD10CM",
							"CONCEPT_CLASS_ID" : "5-char billing code"
						},
						"isExcluded" : false,
						"includeDescendants" : true,
						"includeMapped" : false
					},
					{
						"concept" : {
							"CONCEPT_ID" : 45586889,
							"CONCEPT_NAME" : "Unilateral primary osteoarthritis, right hip",
							"STANDARD_CONCEPT" : "N",
							"STANDARD_CONCEPT_CAPTION" : "Non-Standard",
							"INVALID_REASON" : "V",
							"INVALID_REASON_CAPTION" : "Valid",
							"CONCEPT_CODE" : "M16.11",
							"DOMAIN_ID" : "Condition",
							"VOCABULARY_ID" : "ICD10CM",
							"CONCEPT_CLASS_ID" : "5-char billing code"
						},
						"isExcluded" : false,
						"includeDescendants" : true,
						"includeMapped" : false
					},
					{
						"concept" : {
							"CONCEPT_ID" : 45577163,
							"CONCEPT_NAME" : "Unilateral primary osteoarthritis, unspecified hip",
							"STANDARD_CONCEPT" : "N",
							"STANDARD_CONCEPT_CAPTION" : "Non-Standard",
							"INVALID_REASON" : "V",
							"INVALID_REASON_CAPTION" : "Valid",
							"CONCEPT_CODE" : "M16.10",
							"DOMAIN_ID" : "Condition",
							"VOCABULARY_ID" : "ICD10CM",
							"CONCEPT_CLASS_ID" : "5-char billing code"
						},
						"isExcluded" : false,
						"includeDescendants" : true,
						"includeMapped" : false
					},
					{
						"concept" : {
							"CONCEPT_ID" : 42536659,
							"CONCEPT_NAME" : "Wear of articular bearing surface of joint prosthesis of hip",
							"STANDARD_CONCEPT" : "S",
							"STANDARD_CONCEPT_CAPTION" : "Standard",
							"INVALID_REASON" : "V",
							"INVALID_REASON_CAPTION" : "Valid",
							"CONCEPT_CODE" : "735602002",
							"DOMAIN_ID" : "Condition",
							"VOCABULARY_ID" : "SNOMED",
							"CONCEPT_CLASS_ID" : "Clinical Finding"
						},
						"isExcluded" : true,
						"includeDescendants" : false,
						"includeMapped" : false
					},
					{
						"concept" : {
							"CONCEPT_ID" : 42539034,
							"CONCEPT_NAME" : "Wear of articular bearing surface of joint prosthesis of knee",
							"STANDARD_CONCEPT" : "S",
							"STANDARD_CONCEPT_CAPTION" : "Standard",
							"INVALID_REASON" : "V",
							"INVALID_REASON_CAPTION" : "Valid",
							"CONCEPT_CODE" : "735603007",
							"DOMAIN_ID" : "Condition",
							"VOCABULARY_ID" : "SNOMED",
							"CONCEPT_CLASS_ID" : "Clinical Finding"
						},
						"isExcluded" : true,
						"includeDescendants" : false,
						"includeMapped" : false
					}
				]
			}
		}
	],
	"QualifiedLimit" : {
		"Type" : "First"
	},
	"ExpressionLimit" : {
		"Type" : "First"
	},
	"InclusionRules" : [],
	"CensoringCriteria" : [],
	"CollapseSettings" : {
		"CollapseType" : "ERA",
		"EraPad" : 0
	},
	"CensorWindow" : {}
}